jhelabtoolkit/__init__.py
jhelabtoolkit/calibration/__init__.py
jhelabtoolkit/calibration/thermal.py
jhelabtoolkit/io/___init__.py
jhelabtoolkit/io/zurich.py
jhelabtoolkit/io/nanosurf/__init__.py
jhelabtoolkit/io/nanosurf/nanosurf.py
jhelabtoolkit/io/nanosurf/nid_components.py
jhelabtoolkit/preprocessing/__init__.py
jhelabtoolkit/preprocessing/spectra.py
jhelabtoolkit/utils/__init__.py
jhelabtoolkit/utils/misc.py
jhelabtoolkit/utils/plotting.py
jhelabtoolkit/utils/xarray.py
jhelabtoolkit-0.1.2.dist-info/LICENSE
jhelabtoolkit-0.1.2.dist-info/WHEEL
jhelabtoolkit-0.1.2.dist-info/METADATA
jhelabtoolkit-0.1.2.dist-info/RECORD
