Metadata-Version: 2.1
Name: jhelabtoolkit
Version: 0.1.2
Summary: Common utility codes used at JheLab for AFM, rheology, and ML research
Author-email: Joon-Hyuk Ko <jhko725@snu.ac.kr>, Hankyul Koh <physics113@snu.ac.kr>, Wonho Jhe <whjhe@snu.ac.kr>
Classifier: License :: OSI Approved :: MIT License
Requires-Dist: numpy
Requires-Dist: xarray
Requires-Dist: pydantic>=1.10
Requires-Dist: scikit-image
Requires-Dist: matplotlib
Project-URL: Home, https://github.com/Jhko725/jhelabtoolkit
